wayfarer/__init__.py
wayfarer/functions.py
wayfarer/io.py
wayfarer/linearref.py
wayfarer/loader.py
wayfarer/loops.py
wayfarer/merger.py
wayfarer/osmnx_compat.py
wayfarer/py.typed
wayfarer/routing.py
wayfarer/splitter.py
wayfarer/validator.py
wayfarer-0.13.2.dist-info/licenses/LICENSE
wayfarer-0.13.2.dist-info/METADATA
wayfarer-0.13.2.dist-info/WHEEL
wayfarer-0.13.2.dist-info/top_level.txt
wayfarer-0.13.2.dist-info/RECORD
