Metadata-Version: 2.4
Name: wayfarer
Version: 0.13.2
Summary: A library to add spatial functions to networkx
Home-page: https://github.com/compassinformatics/wayfarer/
Author: Seth Girvin
Author-email: sgirvin@compass.ie
License: MIT
Classifier: Development Status :: 4 - Beta
Classifier: License :: OSI Approved :: MIT License
Classifier: Programming Language :: Python :: 3.10
Classifier: Intended Audience :: Developers
License-File: LICENSE
Requires-Dist: networkx>=3.0
Requires-Dist: geojson
Dynamic: author
Dynamic: author-email
Dynamic: classifier
Dynamic: description
Dynamic: home-page
Dynamic: license
Dynamic: license-file
Dynamic: requires-dist
Dynamic: summary
